{
    "info": "None",
    "foclen": 88.6115,
    "fnum": 4.6764,
    "r_sensor": 21.6,
    "(d_sensor)": 109.25,
    "(sensor_size)": [
        30.547,
        30.547
    ],
    "surfaces": [
        {
            "idx": 1,
            "type": "Plane",
            "(l)": 37.47665940288702,
            "r": 15.556590270996093,
            "(d)": 0.0,
            "is_square": true,
            "mat2": "n-sf10",
            "d_next": 6.725
        },
        {
            "idx": 2,
            "type": "Anamorphic",
            "r": 14.1259,
            "cx": 0.0266,
            "roc_x": 37.5352,
            "cy": 0.0,
            "roc_y": 1000000028.2819,
            "d": 6.725,
            "mat2": "air",
            "d_next": 17.78
        },
        {
            "idx": 3,
            "type": "Anamorphic",
            "r": 17.6691,
            "cx": 0.02,
            "roc_x": 49.9376,
            "cy": 0.0,
            "roc_y": 1000000028.2819,
            "d": 24.505,
            "mat2": "1.7283/28.53",
            "d_next": 3.995
        },
        {
            "idx": 4,
            "type": "Plane",
            "(l)": 24.748737341529164,
            "r": 17.5,
            "(d)": 28.5,
            "is_square": true,
            "mat2": "air",
            "d_next": 2.0
        },
        {
            "idx": 5,
            "type": "Aperture",
            "r": 17.5,
            "(d)": 30.5,
            "mat2": "air",
            "is_square": false,
            "diffraction": false,
            "d_next": 78.75
        }
    ]
}